pysspm_rhythia/__init__.py
pysspm_rhythia/__version__.py
pysspm_rhythia/extras.py
pysspm_rhythia/parser.py
pysspm_rhythia/pysspm.py
pysspm_rhythia-2.0.0.dist-info/LICENSE
pysspm_rhythia-2.0.0.dist-info/METADATA
pysspm_rhythia-2.0.0.dist-info/WHEEL
pysspm_rhythia-2.0.0.dist-info/top_level.txt
pysspm_rhythia-2.0.0.dist-info/RECORD
