Metadata-Version: 2.1
Name: pysspm-rhythia
Version: 2.0.0
Summary: A Python library dedicated to reading, writing, and modifying the Rhythia SSPM (.sspm) file format
Author-email: David Jedlovsky <Dev.DavidJed@gmail.com>
License: LGPL-3.0
Project-URL: Homepage, https://github.com/David-Jed/pysspm
Project-URL: Issues, https://github.com/David-Jed/pysspm/issues
Keywords: Rhythia,Sound space,SSPM,Rhythm game,pysspm-rhythia,pysspm,nova,phoenyx,SS+M,sspm
Classifier: Programming Language :: Python :: 3
Classifier: Operating System :: OS Independent
Requires-Python: >=3.7
License-File: LICENSE
